bencode/__init__.py
bencode/bencode.py
bencode/py.typed
bencode/torrent.py
bencode/transform.py
modern_bencode-1.6.1.dist-info/LICENSE
modern_bencode-1.6.1.dist-info/METADATA
modern_bencode-1.6.1.dist-info/WHEEL
modern_bencode-1.6.1.dist-info/top_level.txt
modern_bencode-1.6.1.dist-info/RECORD
