Metadata-Version: 2.1
Name: modern-bencode
Version: 1.6.1
Summary: A simple bencode library
Home-page: https://github.com/retonato/modern-bencode
License: UNKNOWN
Platform: UNKNOWN
Requires-Python: >=3.7
